.autoenv.zsh
.readthedocs.yml
AUTHORS
ChangeLog
LICENSE
README.md
docutil.conf
requirements-dev.in
requirements-dev.txt
requirements.in
requirements.txt
setup.cfg
setup.py
tox.ini
docs/Makefile
docs/conf.py
docs/development.rst
docs/index.rst
docs/release-notes.rst
docs/_static/theme_overrides.css
tests/__init__.py
tests/conftest.py
tests/test_db.kdbx
tests/test_keepass_import.py
vault_keepass_import/__init__.py
vault_keepass_import/main.py
vault_keepass_import/version.py
vault_keepass_import.egg-info/PKG-INFO
vault_keepass_import.egg-info/SOURCES.txt
vault_keepass_import.egg-info/dependency_links.txt
vault_keepass_import.egg-info/entry_points.txt
vault_keepass_import.egg-info/not-zip-safe
vault_keepass_import.egg-info/pbr.json
vault_keepass_import.egg-info/requires.txt
vault_keepass_import.egg-info/top_level.txt